trie/__init__.py
trie/trie.py
trie_autocomplete-0.1.2.post3.dist-info/LICENSE
trie_autocomplete-0.1.2.post3.dist-info/METADATA
trie_autocomplete-0.1.2.post3.dist-info/WHEEL
trie_autocomplete-0.1.2.post3.dist-info/top_level.txt
trie_autocomplete-0.1.2.post3.dist-info/RECORD
