Metadata-Version: 2.1
Name: trie-autocomplete
Version: 0.1.2.post3
Summary: Autocomplete class using trie
Home-page: UNKNOWN
Author: UNKNOWN
Author-email: hambardzumyanarsen99@gmail.com
License: UNKNOWN
Platform: UNKNOWN
Classifier: Programming Language :: Python :: 3
Classifier: Development Status :: 3 - Alpha
